LibMGE/Audio.py
LibMGE/Audio.pyi
LibMGE/Button.py
LibMGE/Camera.py
LibMGE/Camera.pyi
LibMGE/CollisionBounds.py
LibMGE/CollisionBounds.pyi
LibMGE/Collisions.py
LibMGE/Collisions.pyi
LibMGE/Color.py
LibMGE/Color.pyi
LibMGE/Common.py
LibMGE/Constants.py
LibMGE/GameController.py
LibMGE/Image.py
LibMGE/Keyboard.py
LibMGE/Line.py
LibMGE/Log.pyd
LibMGE/Log.pyi
LibMGE/Material.py
LibMGE/Mesh.py
LibMGE/Monitors.py
LibMGE/Mouse.py
LibMGE/Object2D.py
LibMGE/Platform.py
LibMGE/Platform.pyi
LibMGE/Text.py
LibMGE/Texture.py
LibMGE/Time.pyd
LibMGE/Time.pyi
LibMGE/Vector.py
LibMGE/Version.py
LibMGE/Window.py
LibMGE/Window.pyi
LibMGE/__init__.py
LibMGE/_ConsoleScripts/__init__.py
LibMGE/_ConsoleScripts/_sdl_introspection.py
LibMGE/_ConsoleScripts/deps.py
LibMGE/_ConsoleScripts/doctor.py
LibMGE/_ConsoleScripts/help.py
LibMGE/_ConsoleScripts/info.py
LibMGE/_InputsEmulator/__init__.py
LibMGE/_InputsEmulator/_error.py
LibMGE/_InputsEmulator/_linux.py
LibMGE/_InputsEmulator/_win32.py
LibMGE/_sdl/__init__.py
LibMGE/_sdl/_dll_loader.py
LibMGE/_sdl/sdl2.py
LibMGE/_sdl/sdlgfx.py
LibMGE/_sdl/sdlimage.py
LibMGE/_sdl/sdlmixer.py
LibMGE/_sdl/sdlttf.py
libmge-1.0.0b11.dist-info/licenses/LICENCE
libmge-1.0.0b11.dist-info/METADATA
libmge-1.0.0b11.dist-info/WHEEL
libmge-1.0.0b11.dist-info/entry_points.txt
libmge-1.0.0b11.dist-info/top_level.txt
libmge-1.0.0b11.dist-info/RECORD
