Metadata-Version: 2.4
Name: LibMGE
Version: 1.0.0b11
Summary: LibMGE is a powerful graphical user interface library for developing 2D programs and games.
Author-email: Lucas Guimarães <commercial@lucasguimaraes.pro>
License: Zlib
Project-URL: Homepage, https://libmge.org/
Project-URL: Source, https://github.com/MonumentalGames/LibMGE
Project-URL: Documentation, https://docs.libmge.org/
Project-URL: Bug Tracker, https://github.com/MonumentalGames/LibMGE/issues
Project-URL: Author Website, https://lucasguimaraes.pro/
Keywords: 2D,game development,graphics,GUI,SDL,game engine,graphics library,animation
Classifier: Development Status :: 4 - Beta
Classifier: Intended Audience :: Developers
Classifier: Topic :: Software Development :: Libraries :: Application Frameworks
Classifier: Topic :: Games/Entertainment
Classifier: Topic :: Multimedia :: Graphics
Classifier: License :: OSI Approved :: zlib/libpng License
Classifier: Programming Language :: Python :: 3
Classifier: Programming Language :: Python :: 3.7
Classifier: Programming Language :: Python :: 3.8
Classifier: Programming Language :: Python :: 3.9
Classifier: Programming Language :: Python :: 3.10
Classifier: Programming Language :: Python :: 3.11
Classifier: Programming Language :: Python :: 3.12
Classifier: Programming Language :: Python :: 3.13
Classifier: Operating System :: Microsoft :: Windows
Classifier: Operating System :: POSIX :: Linux
Requires-Python: >=3.5
License-File: LICENCE
Requires-Dist: numpy
Dynamic: license-file
